openllm_core/__init__.py
openllm_core/_configuration.py
openllm_core/_schemas.py
openllm_core/_typing_compat.py
openllm_core/_version.py
openllm_core/exceptions.py
openllm_core/py.typed
openllm_core/config/__init__.py
openllm_core/config/configuration_auto.py
openllm_core/config/configuration_baichuan.py
openllm_core/config/configuration_chatglm.py
openllm_core/config/configuration_commandr.py
openllm_core/config/configuration_dbrx.py
openllm_core/config/configuration_dolly_v2.py
openllm_core/config/configuration_falcon.py
openllm_core/config/configuration_gemma.py
openllm_core/config/configuration_gpt_neox.py
openllm_core/config/configuration_llama.py
openllm_core/config/configuration_mistral.py
openllm_core/config/configuration_mixtral.py
openllm_core/config/configuration_mpt.py
openllm_core/config/configuration_opt.py
openllm_core/config/configuration_phi.py
openllm_core/config/configuration_qwen.py
openllm_core/config/configuration_stablelm.py
openllm_core/config/configuration_starcoder.py
openllm_core/config/configuration_yi.py
openllm_core/protocol/__init__.py
openllm_core/protocol/openai.py
openllm_core/utils/__init__.py
openllm_core/utils/__init__.pyi
openllm_core/utils/_constants.py
openllm_core/utils/analytics.py
openllm_core/utils/codegen.py
openllm_core/utils/dantic.py
openllm_core/utils/import_utils.py
openllm_core/utils/import_utils.pyi
openllm_core/utils/lazy.py
openllm_core/utils/peft.py
openllm_core/utils/pkg.py
openllm_core/utils/representation.py
openllm_core/utils/serde.py
openllm_core-0.5.7.dist-info/METADATA
openllm_core-0.5.7.dist-info/WHEEL
openllm_core-0.5.7.dist-info/licenses/LICENSE.md
openllm_core-0.5.7.dist-info/RECORD
