Metadata-Version: 2.1
Name: openllm-core
Version: 0.5.7
Summary: OpenLLM Core: Core components for OpenLLM.
Project-URL: Blog, https://modelserving.com
Project-URL: Chat, https://l.bentoml.com/join-openllm-discord
Project-URL: Documentation, https://github.com/bentoml/OpenLLM/blob/main/openllm-core/README.md
Project-URL: GitHub, https://github.com/bentoml/OpenLLM/blob/main/openllm-core
Project-URL: History, https://github.com/bentoml/OpenLLM/blob/main/CHANGELOG.md
Project-URL: Homepage, https://bentoml.com
Project-URL: Tracker, https://github.com/bentoml/OpenLLM/issues
Project-URL: Twitter, https://twitter.com/bentomlai
Author-email: Aaron Pham <aarnphm@bentoml.com>, BentoML Team <contact@bentoml.com>
License-Expression: Apache-2.0
License-File: LICENSE.md
Keywords: AI,Alpaca,BentoML,Falcon,Fine tuning,Generative AI,LLMOps,Large Language Model,Llama 2,MLOps,Model Deployment,Model Serving,PyTorch,Serverless,StableLM,Transformers,Vicuna
Classifier: Development Status :: 5 - Production/Stable
Classifier: Environment :: GPU :: NVIDIA CUDA
Classifier: Environment :: GPU :: NVIDIA CUDA :: 11.7
Classifier: Environment :: GPU :: NVIDIA CUDA :: 11.8
Classifier: Environment :: GPU :: NVIDIA CUDA :: 12
Classifier: Intended Audience :: Developers
Classifier: Intended Audience :: Science/Research
Classifier: Intended Audience :: System Administrators
Classifier: License :: OSI Approved :: Apache Software License
Classifier: Operating System :: OS Independent
Classifier: Programming Language :: Python
Classifier: Programming Language :: Python :: 3
Classifier: Programming Language :: Python :: 3 :: Only
Classifier: Programming Language :: Python :: 3.8
Classifier: Programming Language :: Python :: 3.9
Classifier: Programming Language :: Python :: 3.10
Classifier: Programming Language :: Python :: 3.11
Classifier: Programming Language :: Python :: Implementation :: CPython
Classifier: Programming Language :: Python :: Implementation :: PyPy
Classifier: Topic :: Scientific/Engineering
Classifier: Topic :: Scientific/Engineering :: Artificial Intelligence
Classifier: Topic :: Software Development :: Libraries
Classifier: Typing :: Typed
Requires-Python: >=3.8
Requires-Dist: attrs>=23.2.0
Requires-Dist: deepmerge
Requires-Dist: inflection
Requires-Dist: mypy-extensions
Requires-Dist: orjson
Requires-Dist: packaging
Requires-Dist: pydantic>2
Requires-Dist: typing-extensions
Provides-Extra: bentoml
Requires-Dist: bentoml>=1.2; extra == 'bentoml'
Provides-Extra: full
Requires-Dist: openllm-core[bentoml]; extra == 'full'
Requires-Dist: transformers>=4.36.0; extra == 'full'
